dosmaster/__init__.py
dosmaster/base/__init__.py
dosmaster/base/data_generation.py
dosmaster/base/package_version_check.py
dosmaster/base/printer.py
dosmaster/custom_setting/example_default.yaml
dosmaster/custom_setting/example_figure_size_up.yaml
dosmaster/custom_setting/example_font_size_up.yaml
dosmaster/features/__init__.py
dosmaster/features/a_add_atom_dos.py
dosmaster/features/b_dos_projection.py
dosmaster/features/c_dos_sum.py
dosmaster/features/d_average_dos.py
dosmaster/features/e_remove_dos.py
dosmaster/features/f_change_sign.py
dosmaster/features/g_graph_editor.py
dosmaster/features/h_axis_optimization.py
dosmaster/features/i_import_custom_setting.py
dosmaster/features/j_save_custom_setting.py
dosmaster/features/k_import_dosmaster_data.py
dosmaster/features/l_save_dosmaster_data.py
dosmaster/features/m_save_plot_script.py
dosmaster/fileparser/__init__.py
dosmaster/fileparser/doscar_split.py
dosmaster/fileparser/procar_parser.py
dosmaster/fileparser/structure_parser.py
dosmaster/main/__init__.py
dosmaster/main/dosmaster.py
dosmaster/mainplotter/__init__.py
dosmaster/mainplotter/dosplot.py
dosmaster/subplotter/__init__.py
dosmaster/subplotter/colors.csv
dosmaster/subplotter/colortable.py
dosmaster/subplotter/dosplot_manager.py
dosmaster/subplotter/make_color_list.py
dosmaster-1.8.24.dist-info/LICENSE
dosmaster-1.8.24.dist-info/METADATA
dosmaster-1.8.24.dist-info/WHEEL
dosmaster-1.8.24.dist-info/entry_points.txt
dosmaster-1.8.24.dist-info/top_level.txt
dosmaster-1.8.24.dist-info/RECORD
