Metadata-Version: 2.1
Name: dosmaster
Version: 1.8.24
Summary: DOS(Density Of States) Plot Smartly in Terminal
Home-page: https://github.com/pyj6767/DOSMaster
Author: Youngjun Park, Jaeseon Kim in CNMD
Author-email: yjpark29@postech.ac.kr
License: MIT
Keywords: vasp dos
Classifier: Development Status :: 4 - Beta
Classifier: Intended Audience :: Science/Research
Classifier: Natural Language :: English
Classifier: Programming Language :: Python :: 3 :: Only
Classifier: Programming Language :: Python :: 3.7
Classifier: Topic :: Scientific/Engineering :: Chemistry
Classifier: Topic :: Scientific/Engineering :: Physics
Classifier: License :: OSI Approved :: MIT License
Requires-Python: >=3.7.13
License-File: LICENSE
Requires-Dist: numpy
Requires-Dist: matplotlib
Requires-Dist: pandas >=1.3.5
Requires-Dist: ase >=3.22.1
Requires-Dist: colorama >=0.4.6
Requires-Dist: PyYAML
Requires-Dist: importlib-metadata
Requires-Dist: requests
